{
  "times": [
    {
      "id": 1,
      "nome": "Arsenal",
      "dono": ""
    },
    {
      "id": 2,
      "nome": "Barcelona",
      "dono": ""
    },
    {
      "id": 3,
      "nome": "Bayern de Munique",
      "dono": ""
    },
    {
      "id": 4,
      "nome": "Botafogo",
      "dono": ""
    },
    {
      "id": 5,
      "nome": "Chelsea",
      "dono": ""
    },
    {
      "id": 6,
      "nome": "Flamengo",
      "dono": ""
    },
    {
      "id": 7,
      "nome": "Manchester City",
      "dono": ""
    },
    {
      "id": 8,
      "nome": "Milan",
      "dono": ""
    }
  ],
  "partidas": [
    {
      "id": 1,
      "rodada": 1,
      "time_casa_id": 2,
      "time_visitante_id": 1,
      "gols_casa": 1,
      "gols_visitante": 0,
      "data_partida": "2025-10-31",
      "eventos": [
        {
          "jogadorId": "PlayerB",
          "tipo": "gol",
          "minuto": "6",
          "partida_id": 1
        }
      ]
    }
  ],
  "jogadores": [
    {
      "id": "PlayerB",
      "nome": "Jogador B",
      "time_id": 2
    }
  ]
}